ssfm_gpu/__init__.py
ssfm_gpu/channel.py
ssfm_gpu/conversion.py
ssfm_gpu/examples.py
ssfm_gpu/propagation.py
ssfm_gpu-0.1.4.dist-info/LICENSE
ssfm_gpu-0.1.4.dist-info/METADATA
ssfm_gpu-0.1.4.dist-info/WHEEL
ssfm_gpu-0.1.4.dist-info/top_level.txt
ssfm_gpu-0.1.4.dist-info/RECORD
