Metadata-Version: 2.1
Name: ssfm-gpu
Version: 0.1.4
Summary: Tensorflow GPU version of split-step Fourier method for Nonlinear Schrodinger and Manakov equations
Author-email: Egor Sedov <e.sedov@g.nsu.ru>
License: MIT License
Project-URL: Homepage, https://github.com/esf0/ssfm-gpu
Project-URL: Bug Tracker, https://github.com/esf0/ssfm-gpu/issues
Classifier: Programming Language :: Python :: 3
Classifier: License :: OSI Approved :: MIT License
Classifier: Operating System :: OS Independent
Classifier: Development Status :: 2 - Pre-Alpha
Classifier: Topic :: Scientific/Engineering
Requires-Python: >=3.7
License-File: LICENSE
